{
  "image": "6642\\6642.jpg",
  "title": "The Empire Of Sand",
  "description": "gud eevnng! welkom 2 The Empire of Sand werr it iz awwayz PAST YOUR BEDTIME NOW gud eevnng! You are welkom back! You hav been heer b4! so You mus b sleeeeeepng You mus b dreeeeamnng untl th morrrrninnng You wil b snorrrrrrring yawwwwwwwwwwwwwwwwwn PAST YOUR BEDTIME NOW. Let us go then You and eye into The Empire Of Sand!",
  "credits": "<strong>Playwright</strong>: Steve Pirot<br><strong>Cast</strong>: Steve Pirot<br/></br>",
  "website": "",
  "plain_language": "",
  "show_type": "<span> <img alt=\"\" src=\"/images/icon_type.svg\"/> </span> Theatre for Young Audiences",
  "price": "<span> <img alt=\"\" src=\"/images/event-icon.svg\"/></span> $15.00 inc $5.00 fee",
  "run": "<span> <img alt=\"\" src=\"/images/calendar.svg\"/> </span> 15-August 24, 2025",
  "playtime": "<span> <img alt=\"\" src=\"/images/icon_duration.svg\"/> </span> 60 minutes",
  "venue": "<span> <img alt=\"\" src=\"/images/location.svg\"/></span>Old Strathcona Public Library",
  "site": "<span> <img alt=\"subvenue\" src=\"/images/subvenue.svg\"/> </span> 10: Old Strathcona Public Library",
  "locationId": 10,
  "location": "10: Old Strathcona Public Library",
  "age": "<span> <img alt=\"\" src=\"/images/age-restriction.svg\"/></span> General (G)",
  "warnings": "",
  "location_html": "<h3>Old Strathcona Public Library</h3> <div class=\"addres-pin\"> <p>8331 104 St NW</p> <p>T6E 4E9</p> </div> <!--<a href=\"#\"></a>--> <span>(780) 496-1828</span> <a href=\"mailto:\"></a> <h3>10: Old Strathcona Public Library</h3> <div class=\"addres-pin\"> <p>8331 104 St NW</p> </div>",
  "map_html": "<iframe allowfullscreen=\"\" height=\"296\" loading=\"lazy\" referrerpolicy=\"no-referrer-when-downgrade\" src=\"https://www.google.com/maps?key=AIzaSyDZTvScmHYmftgyIKzsmX3MW7t4sDhxUcg&amp;layer=c&amp;q=53.51990000,-113.49760000&amp;z=17&amp;output=embed\" style=\"border:0\" width=\"100%\"> </iframe>",
  "performances": {
    "dates": [
      "2025-08-15",
      "2025-08-17",
      "2025-08-18",
      "2025-08-19",
      "2025-08-20",
      "2025-08-21",
      "2025-08-22",
      "2025-08-23",
      "2025-08-24"
    ],
    "times": {
      "2025-08-15": [
        {
          "id": "601:43289",
          "title": null,
          "description": null,
          "presentationFormat": "PHYSICAL",
          "performanceTime": "14:45",
          "performanceRealTime": "2025-08-15 14:45:00",
          "performanceDate": "15th August 2025 14:45",
          "availability": 64,
          "reserved": false,
          "contentUrl": null,
          "admissionTime": "",
          "cssClass": "green"
        }
      ],
      "2025-08-17": [
        {
          "id": "601:43290",
          "title": null,
          "description": null,
          "presentationFormat": "PHYSICAL",
          "performanceTime": "11:00",
          "performanceRealTime": "2025-08-17 11:00:00",
          "performanceDate": "17th August 2025 11:00",
          "availability": 64,
          "reserved": false,
          "contentUrl": null,
          "admissionTime": "",
          "cssClass": "green"
        }
      ],
      "2025-08-18": [
        {
          "id": "601:43997",
          "title": null,
          "description": null,
          "presentationFormat": "PHYSICAL",
          "performanceTime": "14:45",
          "performanceRealTime": "2025-08-18 14:45:00",
          "performanceDate": "18th August 2025 14:45",
          "availability": 64,
          "reserved": false,
          "contentUrl": null,
          "admissionTime": "",
          "cssClass": "green"
        }
      ],
      "2025-08-19": [
        {
          "id": "601:43291",
          "title": null,
          "description": null,
          "presentationFormat": "PHYSICAL",
          "performanceTime": "14:45",
          "performanceRealTime": "2025-08-19 14:45:00",
          "performanceDate": "19th August 2025 14:45",
          "availability": 64,
          "reserved": false,
          "contentUrl": null,
          "admissionTime": "",
          "cssClass": "green"
        }
      ],
      "2025-08-20": [
        {
          "id": "601:43292",
          "title": null,
          "description": null,
          "presentationFormat": "PHYSICAL",
          "performanceTime": "13:00",
          "performanceRealTime": "2025-08-20 13:00:00",
          "performanceDate": "20th August 2025 13:00",
          "availability": 64,
          "reserved": false,
          "contentUrl": null,
          "admissionTime": "",
          "cssClass": "green"
        }
      ],
      "2025-08-21": [
        {
          "id": "601:43293",
          "title": null,
          "description": null,
          "presentationFormat": "PHYSICAL",
          "performanceTime": "12:45",
          "performanceRealTime": "2025-08-21 12:45:00",
          "performanceDate": "21st August 2025 12:45",
          "availability": 64,
          "reserved": false,
          "contentUrl": null,
          "admissionTime": "",
          "cssClass": "green"
        }
      ],
      "2025-08-22": [
        {
          "id": "601:43998",
          "title": null,
          "description": null,
          "presentationFormat": "PHYSICAL",
          "performanceTime": "11:00",
          "performanceRealTime": "2025-08-22 11:00:00",
          "performanceDate": "22nd August 2025 11:00",
          "availability": 64,
          "reserved": false,
          "contentUrl": null,
          "admissionTime": "",
          "cssClass": "green"
        }
      ],
      "2025-08-23": [
        {
          "id": "601:43294",
          "title": null,
          "description": null,
          "presentationFormat": "PHYSICAL",
          "performanceTime": "11:00",
          "performanceRealTime": "2025-08-23 11:00:00",
          "performanceDate": "23rd August 2025 11:00",
          "availability": 64,
          "reserved": false,
          "contentUrl": null,
          "admissionTime": "",
          "cssClass": "green"
        }
      ],
      "2025-08-24": [
        {
          "id": "601:43295",
          "title": null,
          "description": null,
          "presentationFormat": "PHYSICAL",
          "performanceTime": "15:00",
          "performanceRealTime": "2025-08-24 15:00:00",
          "performanceDate": "24th August 2025 15:00",
          "availability": 64,
          "reserved": false,
          "contentUrl": null,
          "admissionTime": "",
          "cssClass": "green"
        }
      ]
    },
    "data": [],
    "eventId": "601:6642",
    "showAvailabilityInCalendar": true
  }
}