{
  "_id": 98,
  "country": null,
  "description": "<p>Hailing from the hollers of southern Indiana, Stephen Wilson Jr. has taken a winding path to his musical career, making stops as a Golden Gloves boxing finalist, scientist, and indie rock band member before finding his voice as a solo artist. His genre-defying debut double album, <i>s\u00f8n of dad</i>, cemented him as a force in country and Americana music. The 22-song collection, dedicated to his late father, was named the Best Album of 2023 by Holler and All Country News, and hailed by Rolling Stone as \u201cthe most existential release of the year.\u201d</p><p></p><p>Concert: Friday, August 8</p><p>Schedule is subject to change</p>",
  "description2": null,
  "discoverable": true,
  "external_id": "1410162287591248240",
  "fanjourney_streaming_link": null,
  "generic1": null,
  "generic2": null,
  "generic3": null,
  "generic4": null,
  "generic5": null,
  "generic6": null,
  "letter": "S",
  "link1": "Website|https://stephenwilsonjr.com/",
  "link2": "Youtube|https://www.youtube.com/watch?v=VsbUKXc3-pY&t=37s",
  "link3": "Spotify|spotify:artist:4DSDa4HvAWqvb3dMHUOAfd",
  "link4": "Instagram|https://www.instagram.com/stephen.wilson.jr",
  "link5": "Facebook|https://www.facebook.com/StephenWilsonJrMusic",
  "link6": null,
  "photo2Credit": null,
  "photoCredit": null,
  "photo_suffix": "20250502041115_e1c0f890",
  "photo_suffix2": "",
  "slug": "stephen-wilson-jr",
  "sort_order": null,
  "style": null,
  "subtitle": "USA",
  "tags": [],
  "title": "Stephen Wilson Jr."
}