{
  "_id": 1015,
  "country": null,
  "description": "<p><i>Concert: Sunday, August 9</i></p><p><i>Days of Sessions: Aug 8- 9</i></p><p><i>Schedule is subject to change</i></p><p></p><p>Trousdale\u2019s debut album, <i>Out of My Mind</i>, earned raves from the likes of the Boston Globe, Consequence, and Atwood Magazine for its powerful songwriting, immaculate harmonies, and ability to bridge gaps between country and indie pop. The group further honed those strengths on the road, finding deeper grooves and learning how to meticulously highlight each of their voices. Their 2025 album, <i>Growing Pains</i>, stares down all the weight of its title, a trio of strong, independent women facing the threats of loneliness, broken hearts, loss, and more, and converting it into transformative, uplifting music.</p>",
  "description2": null,
  "discoverable": true,
  "external_id": "1674992928231481752",
  "fanjourney_streaming_link": null,
  "generic1": null,
  "generic2": null,
  "generic3": null,
  "generic4": null,
  "generic5": null,
  "generic6": null,
  "letter": "T",
  "link1": "Website|https://www.trousdalemusic.com/",
  "link2": "Youtube|https://www.youtube.com/watch?v=dagRuKVoZ3Q",
  "link3": "Instagram|https://www.instagram.com/trousdalemusic/?hl=en",
  "link4": "Spotify|spotify:artist:26DvqLYszG0oIOeelTF5kE",
  "link5": "Bandcamp|https://trousdale.bandcamp.com/",
  "link6": "Facebook|https://www.facebook.com/trousdalemusic/",
  "photo2Credit": null,
  "photoCredit": null,
  "photo_suffix": "20260605073155_81a1a46f",
  "photo_suffix2": "",
  "slug": "trousdale",
  "sort_order": null,
  "style": null,
  "subtitle": "USA",
  "tags": [],
  "title": "Trousdale"
}